buzzoff/__init__.py
buzzoff/__main__.py
buzzoff-1.1.0.dist-info/LICENSE
buzzoff-1.1.0.dist-info/METADATA
buzzoff-1.1.0.dist-info/WHEEL
buzzoff-1.1.0.dist-info/entry_points.txt
buzzoff-1.1.0.dist-info/top_level.txt
buzzoff-1.1.0.dist-info/RECORD
